plain/flags/CHANGELOG.md
plain/flags/README.md
plain/flags/__init__.py
plain/flags/admin.py
plain/flags/bridge.py
plain/flags/config.py
plain/flags/default_settings.py
plain/flags/exceptions.py
plain/flags/flags.py
plain/flags/models.py
plain/flags/preflight.py
plain/flags/py.typed
plain/flags/templates.py
plain/flags/utils.py
plain/flags/migrations/0001_initial.py
plain/flags/migrations/0002_remove_flag_plainflags_flag_unique_uuid_and_more.py
plain/flags/migrations/__init__.py
plain/flags/templates/admin/plainflags/flagresult_form.html
plain_flags-0.33.0.dist-info/METADATA
plain_flags-0.33.0.dist-info/WHEEL
plain_flags-0.33.0.dist-info/licenses/LICENSE
plain_flags-0.33.0.dist-info/RECORD
