Metadata-Version: 2.4
Name: plain.flags
Version: 0.33.0
Summary: Local feature flags via database models.
Author-email: Dave Gaeddert <dave.gaeddert@dropseed.dev>
License-Expression: BSD-3-Clause
License-File: LICENSE
Requires-Python: >=3.13
Requires-Dist: plain<1.0.0
